simple_calculator_function/__init__.py
simple_calculator_function/calculator.py
simple_calculator_function/tests.py
simple_calculator_function/.ipynb_checkpoints/__init__-checkpoint.py
simple_calculator_function-0.3.dist-info/LICENSE
simple_calculator_function-0.3.dist-info/WHEEL
simple_calculator_function-0.3.dist-info/METADATA
simple_calculator_function-0.3.dist-info/RECORD
