Metadata-Version: 2.1
Name: simple_calculator_function
Version: 0.3
Summary: CALCULATOR PROGRAM
Author-email: Karan K <karankarnik47@gmail.com>
Classifier: License :: OSI Approved :: MIT License
Project-URL: Home, https://github.com/helloworld4774/simple_calculator
